ooler_ble_client/__init__.py
ooler_ble_client/advertisement.py
ooler_ble_client/check_connection.py
ooler_ble_client/client.py
ooler_ble_client/const.py
ooler_ble_client/models.py
ooler_ble_client/pair.py
ooler_ble_client-0.7.1.dist-info/METADATA
ooler_ble_client-0.7.1.dist-info/WHEEL
ooler_ble_client-0.7.1.dist-info/RECORD
